odoo/addons/invoices_menu_item/README.rst
odoo/addons/invoices_menu_item/__init__.py
odoo/addons/invoices_menu_item/__manifest__.py
odoo/addons/invoices_menu_item/i18n/es.po
odoo/addons/invoices_menu_item/static/description/icon.png
odoo/addons/invoices_menu_item/views/account_invoice.xml
odoo12_addon_invoices_menu_item-12.0.1.0.0.dist-info/METADATA
odoo12_addon_invoices_menu_item-12.0.1.0.0.dist-info/WHEEL
odoo12_addon_invoices_menu_item-12.0.1.0.0.dist-info/top_level.txt
odoo12_addon_invoices_menu_item-12.0.1.0.0.dist-info/RECORD
